oceantide/__init__.py
oceantide/cli.py
oceantide/constituents.py
oceantide/ellipse.py
oceantide/tide.py
oceantide/core/__init__.py
oceantide/core/attributes.yml
oceantide/core/otis.py
oceantide/core/utils.py
oceantide/input/__init__.py
oceantide/input/oceantide.py
oceantide/input/otis_atlas_netcdf.py
oceantide/input/otis_binary.py
oceantide/input/otis_netcdf.py
oceantide/output/__init__.py
oceantide/output/oceantide.py
oceantide/output/otis_binary.py
oceantide/output/otis_netcdf.py
oceantide-0.7.1.dist-info/licenses/AUTHORS.rst
oceantide-0.7.1.dist-info/licenses/LICENSE
oceantide-0.7.1.dist-info/METADATA
oceantide-0.7.1.dist-info/WHEEL
oceantide-0.7.1.dist-info/entry_points.txt
oceantide-0.7.1.dist-info/top_level.txt
oceantide-0.7.1.dist-info/RECORD
