Metadata-Version: 2.4
Name: oceantide
Version: 0.7.1
Summary: Library for ocean tide prediction
Author-email: Oceanum Ltd <developers@oceanum.science>
Maintainer-email: Rafael Guedes <r.guedes@oceanum.science>
License: MIT License
Project-URL: Source, https://github.com/oceanum/oceantide
Project-URL: Tracker, https://github.com/oceanum/oceantide/issues
Project-URL: Changelog, https://github.com/oceanum/oceantide/blob/main/HISTORY.rst
Keywords: ocean,tide,prediction,constituents,xarray,otis
Classifier: Development Status :: 4 - Beta
Classifier: Intended Audience :: Science/Research
Classifier: License :: OSI Approved :: MIT License
Classifier: Natural Language :: English
Classifier: Operating System :: OS Independent
Classifier: Topic :: Scientific/Engineering
Classifier: Topic :: Scientific/Engineering :: Physics
Classifier: Topic :: Scientific/Engineering :: Visualization
Classifier: Programming Language :: Python :: 3
Classifier: Programming Language :: Python :: 3.8
Classifier: Programming Language :: Python :: 3.9
Classifier: Programming Language :: Python :: 3.10
Classifier: Programming Language :: Python :: 3.11
Requires-Python: >=3.8
License-File: LICENSE
License-File: AUTHORS.rst
Requires-Dist: click
Requires-Dist: dask
Requires-Dist: netcdf4
Requires-Dist: numpy
Requires-Dist: scipy
Requires-Dist: xarray
Requires-Dist: zarr
Provides-Extra: test
Requires-Dist: pytest; extra == "test"
Provides-Extra: extra
Requires-Dist: gcsfs; extra == "extra"
Provides-Extra: docs
Requires-Dist: pydata-sphinx-theme; extra == "docs"
Requires-Dist: sphinx; extra == "docs"
Requires-Dist: sphinxcontrib-programoutput; extra == "docs"
Dynamic: license-file
